PyEvalis/NaiveBayes.py
PyEvalis/PCA.py
PyEvalis/SVM.py
PyEvalis/Topsis.py
PyEvalis/__init__.py
PyEvalis/__main__.py
PyEvalis/classification/DecisionTree.py
PyEvalis/classification/KNN.py
PyEvalis/classification/LogisticRegression.py
PyEvalis/classification/RandomForest.py
PyEvalis/classification/__init__.py
PyEvalis/clustering/KMeans.py
PyEvalis/clustering/__init__.py
PyEvalis/regression/LinearRegression.py
PyEvalis/regression/__init__.py
PyEvalis/stats/__init__.py
PyEvalis/stats/stats.py
pyevalis-0.0.6.dist-info/METADATA
pyevalis-0.0.6.dist-info/WHEEL
pyevalis-0.0.6.dist-info/entry_points.txt
pyevalis-0.0.6.dist-info/top_level.txt
pyevalis-0.0.6.dist-info/RECORD
