Metadata-Version: 2.1
Name: pyevalis
Version: 0.0.6
Summary: Python package for PyEvalis
Home-page: https://github.com/Guryansh/temp7
Author: Guryansh
Author-email: guryanshsingla@gmail.com
License: MIT
Project-URL: Documentation, https://pyevalis.readthedocs.io/
Classifier: License :: OSI Approved :: MIT License
Classifier: Programming Language :: Python :: 3
Classifier: Programming Language :: Python :: 3.6
Classifier: Programming Language :: Python :: 3.7
Classifier: Programming Language :: Python :: 3.8
Classifier: Programming Language :: Python :: 3.9
Requires-Dist: pandas
Requires-Dist: numpy
Requires-Dist: matplotlib
Requires-Dist: ipython
Requires-Dist: ipywidgets
Requires-Dist: seaborn
Requires-Dist: tabulate
